lightbox/__init__.py
lightbox/animation.py
lightbox/cli.py
lightbox/core.py
lightbox/integrity.py
lightbox/models.py
lightbox/py.typed
lightbox/storage.py
lightbox/integrations/__init__.py
lightbox/integrations/langchain.py
lightbox_rec-0.1.0.dist-info/METADATA
lightbox_rec-0.1.0.dist-info/WHEEL
lightbox_rec-0.1.0.dist-info/entry_points.txt
lightbox_rec-0.1.0.dist-info/licenses/LICENSE
lightbox_rec-0.1.0.dist-info/RECORD
