Metadata-Version: 2.4
Name: lightbox-rec
Version: 0.1.0
Summary: Flight recorder for AI agents - append-only, tamper-evident tool execution logs
Project-URL: Homepage, https://uselightbox.app
Project-URL: Documentation, https://github.com/robertkeenan/lightbox#readme
Project-URL: Repository, https://github.com/robertkeenan/lightbox
Project-URL: Issues, https://github.com/robertkeenan/lightbox/issues
Project-URL: Changelog, https://github.com/robertkeenan/lightbox/blob/main/CHANGELOG.md
Author-email: Robert Keenan <rob@uselightbox.app>
License-Expression: MIT
License-File: LICENSE
Keywords: agents,ai,langchain,logging,observability,tracing
Classifier: Development Status :: 3 - Alpha
Classifier: Intended Audience :: Developers
Classifier: License :: OSI Approved :: MIT License
Classifier: Programming Language :: Python :: 3.12
Classifier: Programming Language :: Python :: 3.13
Classifier: Typing :: Typed
Requires-Python: >=3.12
Requires-Dist: click>=8.0
Provides-Extra: all
Requires-Dist: langchain-core>=0.3; extra == 'all'
Requires-Dist: mypy>=1.10; extra == 'all'
Requires-Dist: pre-commit>=3.7; extra == 'all'
Requires-Dist: pytest-cov>=4.0; extra == 'all'
Requires-Dist: pytest>=8.0; extra == 'all'
Requires-Dist: ruff>=0.4; extra == 'all'
Provides-Extra: dev
Requires-Dist: mypy>=1.10; extra == 'dev'
Requires-Dist: pre-commit>=3.7; extra == 'dev'
Requires-Dist: pytest-cov>=4.0; extra == 'dev'
Requires-Dist: pytest>=8.0; extra == 'dev'
Requires-Dist: ruff>=0.4; extra == 'dev'
Provides-Extra: langchain
Requires-Dist: langchain-core>=0.3; extra == 'langchain'
